PyTableParser/PyTableParser.py
PyTableParser-1.dist-info/LICENSE
PyTableParser-1.dist-info/METADATA
PyTableParser-1.dist-info/WHEEL
PyTableParser-1.dist-info/entry_points.txt
PyTableParser-1.dist-info/top_level.txt
PyTableParser-1.dist-info/RECORD
